shellwords-0.1.0.dist-info/top_level.txt
shellwords-0.1.0.dist-info/metadata.json
shellwords-0.1.0.dist-info/RECORD
shellwords-0.1.0.dist-info/WHEEL
shellwords-0.1.0.dist-info/DESCRIPTION.rst
shellwords-0.1.0.dist-info/METADATA
shellwords/__init__.py
