Metadata-Version: 2.0
Name: shellwords
Version: 0.1.0
Summary: Parse line as shell words.
Home-page: https://github.com/mozillazg/python-shellwords
Author: mozillazg
Author-email: mozillazg101@gmail.com
License: MIT
Keywords: shell,shellwords
Platform: UNKNOWN
Classifier: Development Status :: 5 - Production/Stable
Classifier: Intended Audience :: Developers
Classifier: License :: OSI Approved :: MIT License
Classifier: Operating System :: OS Independent
Classifier: Programming Language :: Python
Classifier: Programming Language :: Python :: 2
Classifier: Programming Language :: Python :: 2.6
Classifier: Programming Language :: Python :: 2.7
Classifier: Programming Language :: Python :: 3
Classifier: Programming Language :: Python :: 3.3
Classifier: Programming Language :: Python :: 3.4
Classifier: Topic :: Utilities
